npg/__init__.py
npg_init-0.3.0.dist-info/METADATA
npg_init-0.3.0.dist-info/RECORD
npg_init-0.3.0.dist-info/WHEEL
npg_init-0.3.0.dist-info/entry_points.txt
npg_init-0.3.0.dist-info/top_level.txt
