Metadata-Version: 2.1
Name: npg-init
Version: 0.3.0
Summary: Creates a directory that sets up basic Python projects
Home-page: https://github.com/KuanHulio/new-package-generator
Author: Sami Altamimi
Author-email: nkjjsami@gmail.com
License: MIT
Platform: UNKNOWN
Classifier: Programming Language :: Python
Classifier: Programming Language :: Python :: 3
Classifier: Programming Language :: Python :: 3.6
